ra_engine/__init__.py
ra_engine/core/__init__.py
ra_engine/core/api.py
ra_engine/core/app.py
ra_engine/ml/__init__.py
ra_engine/ml/classification.py
ra_engine/ml/evaluators.py
ra_engine/ml/regression.py
ra_engine/ml/timeseries.py
ra_engine/runners/__init__.py
ra_engine/runners/ml.py
ra_engine/type_def/__init__.py
ra_engine/type_def/creds.py
ra_engine/type_def/ml.py
ra_engine/type_def/results.py
tests/__init__.py
tests/test.py
tests/test_classification.py
tests/test_regression.py
ra_engine-0.0.1.post7.dist-info/METADATA
ra_engine-0.0.1.post7.dist-info/WHEEL
ra_engine-0.0.1.post7.dist-info/top_level.txt
ra_engine-0.0.1.post7.dist-info/RECORD
